{
	"entries": [
		{
				"message": "Running 01_Run Chrome.script",
				"identifier": "START",
				"timestamp": "2018-12-12 11:49:36.076 +0900"
			},
		{
				"handlerName": "on_01_run_chrome",
				"timestamp": "2018-12-12 11:49:36.717 +0900",
				"message": "[windowsKey]r",
				"scriptName": "01_Run Chrome.script",
				"handlerLine": 3,
				"identifier": "typetext"
			},
		{
				"handlerName": "on_01_run_chrome",
				"timestamp": "2018-12-12 11:49:37.606 +0900",
				"message": "chrome",
				"scriptName": "01_Run Chrome.script",
				"handlerLine": 4,
				"identifier": "typetext"
			},
		{
				"handlerName": "on_01_run_chrome",
				"timestamp": "2018-12-12 11:49:38.339 +0900",
				"message": "[returnKey]",
				"scriptName": "01_Run Chrome.script",
				"handlerLine": 5,
				"identifier": "typetext"
			},
		{
				"handlerName": "on_01_run_chrome",
				"timestamp": "2018-12-12 11:49:39.089 +0900",
				"message": "[windowsAltKey][F4]",
				"scriptName": "01_Run Chrome.script",
				"handlerLine": 6,
				"identifier": "typetext"
			},
		{
				"message": "(Duration:\"3.091\", Errors:\"0\", Exceptions:\"0\", StartTime:\"2018-12-12 11:49:36 +0900\", Successes:\"1\", TestCase:\"01_Run Chrome.script\", Warnings:\"0\")",
				"identifier": "EndTestCase",
				"timestamp": "2018-12-12 11:49:39.167 +0900"
			},
		{
				"message": "Execution Time 0:00:03 01_Run Chrome.script",
				"identifier": "SUCCESS",
				"timestamp": "2018-12-12 11:49:39.198 +0900"
			}
	],
	"createdTimestamp": "2018-12-12 02:49:36.076 +0000"
}